pymdea/__init__.py
pymdea/core.py
pymdea/plot.py
pymdea-0.5.0.dist-info/METADATA
pymdea-0.5.0.dist-info/WHEEL
pymdea-0.5.0.dist-info/licenses/LICENSE
pymdea-0.5.0.dist-info/RECORD
