Metadata-Version: 2.4
Name: pymdea
Version: 0.5.0
Summary: Modified diffusion entropy analysis; a temporal complexity analysis method
Project-URL: Documentation, https://garland-culbreth.github.io/pymdea
Project-URL: Repository, https://github.com/garland-culbreth/pymdea
Project-URL: Issues, https://github.com/garland-culbreth/pymdea/issues
Author: Jacob Baxley, David Lambert
Author-email: Garland Culbreth <culbreth.garland@gmail.com>
Maintainer-email: Garland Culbreth <culbreth.garland@gmail.com>
License: MIT License
License-File: LICENSE
Classifier: Development Status :: 4 - Beta
Classifier: Intended Audience :: Science/Research
Classifier: License :: OSI Approved :: MIT License
Classifier: Programming Language :: Python :: 3.11
Classifier: Programming Language :: Python :: 3.12
Classifier: Topic :: Scientific/Engineering :: Bio-Informatics
Classifier: Topic :: Scientific/Engineering :: Information Analysis
Classifier: Topic :: Scientific/Engineering :: Physics
Requires-Python: >=3.11
Requires-Dist: ipykernel>=6.29.5
Requires-Dist: ipywidgets>=8.1.5
Requires-Dist: logging>=0.4.9.6
Requires-Dist: matplotlib>=3.9.2
Requires-Dist: mkdocs-material>=9.5.33
Requires-Dist: mkdocstrings[python]>=0.25.2
Requires-Dist: numpy>=1.19.0
Requires-Dist: pandas>2.2.2
Requires-Dist: pathlib>=1.0.1
Requires-Dist: polars>=1.5.0
Requires-Dist: pre-commit>=4.1.0
Requires-Dist: pytest>=8.3.2
Requires-Dist: rich>=13.9.4
Requires-Dist: scipy>=1.14.1
Requires-Dist: seaborn>=0.13.2
Requires-Dist: stochastic>=0.6.0
Requires-Dist: typing>=3.10.0.0
